pyrot13/__init__.py
pyrot13/__main__.py
pyrot13-0.1.0.dist-info/LICENSE
pyrot13-0.1.0.dist-info/METADATA
pyrot13-0.1.0.dist-info/WHEEL
pyrot13-0.1.0.dist-info/top_level.txt
pyrot13-0.1.0.dist-info/RECORD
