Metadata-Version: 2.1
Name: pyrot13
Version: 0.1.0
Summary: pyrot13 rotate letters by 13 place.
Home-page: https://github.com/bbriano/pyrot13
Author: Briano Goestiawan
Author-email: b@briano.io
Classifier: Programming Language :: Python :: 3
Classifier: Operating System :: OS Independent
Classifier: License :: OSI Approved :: ISC License (ISCL)
Requires-Python: >=3
License-File: LICENSE
